data_analysis/Example.py
data_analysis/Example.py.py
data_analysis/__init__.py
data_analysis/cleaning.py
data_analysis/setup.py
data_analysis/statistics.py
data_analysis/statistics.py.py
data_analysis/visualization.py
data_analysis/visualization.py.py
tests/__init__.py
tests/test_cleaning.py
tests/test_statistics.py
tests/test_visualization.py
data_analysis_package-0.1.dist-info/METADATA
data_analysis_package-0.1.dist-info/WHEEL
data_analysis_package-0.1.dist-info/top_level.txt
data_analysis_package-0.1.dist-info/RECORD
