Metadata-Version: 2.1
Name: data_analysis_package
Version: 0.1
Summary: A custom data analysis package.
Author: Dhavasu
License: MIT
Requires-Dist: pandas
Requires-Dist: matplotlib
Requires-Dist: seaborn
Requires-Dist: scipy
